llm_play.py
llm_play-0.1.2.dist-info/METADATA
llm_play-0.1.2.dist-info/WHEEL
llm_play-0.1.2.dist-info/entry_points.txt
llm_play-0.1.2.dist-info/licenses/LICENSE
llm_play-0.1.2.dist-info/RECORD
