Metadata-Version: 2.4
Name: llm-play
Version: 0.1.2
Summary: a tool that queries LLMs, analyzes responses, and executes experimental pipelines
License-File: LICENSE
Requires-Python: >=3.8
Requires-Dist: anthropic>=0.42.0
Requires-Dist: inquirerpy>=0.3.4
Requires-Dist: mistletoe>=1.4.0
Requires-Dist: openai>=1.59.7
Requires-Dist: pyyaml>=6.0.2
Requires-Dist: wcwidth>=0.2.13
